{"displayFieldName":"","fieldAliases":{"FID":"FID","NO":"NO","規制条件":"規制条件","路線名":"路線名","危険内容":"危険内容","迂回路":"迂回路","備考":"備考","地先名":"地先名"},"geometryType":"esriGeometryPoint","spatialReference":{"wkid":null},"fields":[{"name":"FID","type":"esriFieldTypeOID","alias":"FID"},{"name":"NO","type":"esriFieldTypeString","alias":"NO","length":254},{"name":"規制条件","type":"esriFieldTypeString","alias":"規制条件","length":254},{"name":"路線名","type":"esriFieldTypeString","alias":"路線名","length":254},{"name":"危険内容","type":"esriFieldTypeString","alias":"危険内容","length":254},{"name":"迂回路","type":"esriFieldTypeString","alias":"迂回路","length":254},{"name":"備考","type":"esriFieldTypeString","alias":"備考","length":254},{"name":"地先名","type":"esriFieldTypeString","alias":"地先名","length":254}],"features":[{"attributes":{"FID":0,"NO":"1","規制条件":"通行止め：連続雨量200mm以上、時間雨量50mm以上","路線名":"国道 １６８号","危険内容":"落石、冠水の恐れ","迂回路":" ","備考":" ","地先名":"新宮市南磐盾\uFF5E新宮市熊野川町・田辺市境界"},"geometry":{"x":135.98013140417092,"y":33.719364985432108}},{"attributes":{"FID":1,"NO":"2","規制条件":"通行止め：連続雨量180mm以上、時間雨量50mm以上","路線名":"国道 １６８号","危険内容":"落石、冠水の恐れ","迂回路":" ","備考":" ","地先名":"新宮市熊野川町・田辺市境界\uFF5E田辺市本宮町土河屋（県境）"},"geometry":{"x":135.80978240518573,"y":33.832018459638313}},{"attributes":{"FID":2,"NO":"3","規制条件":"通行止め：連続雨量180mm以上、時間雨量50mm以上","路線名":"国道 １６９号","危険内容":"落石、冠水の恐れ","迂回路":" ","備考":" ","地先名":"新宮市熊野川町宮井\uFF5E新宮市熊野川町九重（県境）"},"geometry":{"x":135.85308861442917,"y":33.833429295288241}},{"attributes":{"FID":3,"NO":"4","規制条件":"通行止め：連続雨量180mm以上、時間雨量50mm以上","路線名":"国道 １６９号","危険内容":"落石、冠水の恐れ","迂回路":" ","備考":" ","地先名":"新宮市熊野川町玉置口(県境）\uFF5E新宮市熊野川町田戸（県境）"},"geometry":{"x":135.87236518845086,"y":33.886703765046846}},{"attributes":{"FID":4,"NO":"5","規制条件":"通行止め：連続雨量180mm以上、時間雨量50mm以上","路線名":"国道 １６９号","危険内容":"落石、冠水の恐れ","迂回路":" ","備考":" ","地先名":"東牟婁郡北山村下尾井\uFF5E東牟婁郡北山村小松"},"geometry":{"x":135.94284730676452,"y":33.940589344913604}},{"attributes":{"FID":5,"NO":"6","規制条件":"通行止め：連続雨量200mm以上、時間雨量50mm以上","路線名":"国道 ３１１号","危険内容":"落石、崩土の恐れ","迂回路":" ","備考":"区域外に情報板A型2基B型1基","地先名":"田辺市鮎川\uFF5E田辺市中辺路町栗栖川"},"geometry":{"x":135.48742359936082,"y":33.731382397788664}},{"attributes":{"FID":6,"NO":"7","規制条件":"通行止め：連続雨量200mm以上、時間雨量50mm以上","路線名":"国道 ３１１号","危険内容":"落石、崩土の恐れ","迂回路":" ","備考":" ","地先名":"田辺市中辺路町栗栖川\uFF5E田辺市中辺路町・本宮町境界"},"geometry":{"x":135.51633914894947,"y":33.791206341817656}},{"attributes":{"FID":7,"NO":"8","規制条件":"通行止め：連続雨量160mm以上、時間雨量50mm以上","路線名":"国道 ３１１号","危険内容":"落石の恐れ","迂回路":" ","備考":" ","地先名":"田辺市中辺路町・本宮町境界\uFF5E田辺市本宮町皆地"},"geometry":{"x":135.67199466143921,"y":33.821876444252034}},{"attributes":{"FID":8,"NO":"25","規制条件":"通行止め：連続雨量160mm以上、時間雨量30mm以上","路線名":"国道 ４２４号","危険内容":"落石、崩土の恐れ","迂回路":" ","備考":" ","地先名":"田辺市龍神村小家\uFF5E田辺市龍神村福井"},"geometry":{"x":135.42773216220547,"y":33.934548223502816}},{"attributes":{"FID":9,"NO":"26","規制条件":"通行止め：連続雨量160mm以上、時間雨量30mm以上","路線名":"国道 ４２４号","危険内容":"落石、崩土の恐れ","迂回路":" ","備考":" ","地先名":"田辺市龍神村福井\uFF5E日高郡みなべ町清川"},"geometry":{"x":135.41930466486693,"y":33.880334128733558}},{"attributes":{"FID":10,"NO":"27","規制条件":"通行止め：連続雨量160mm以上、時間雨量30mm以上","路線名":"国道 ４２４号","危険内容":"落石、崩土の恐れ","迂回路":" ","備考":" ","地先名":"日高郡みなべ町清川\uFF5E日高郡みなべ町西本庄"},"geometry":{"x":135.39837737372608,"y":33.852976729300408}},{"attributes":{"FID":11,"NO":"28","規制条件":"通行止め：連続雨量160mm以上、時間雨量30mm以上","路線名":"国道 ４２５号","危険内容":"落石、崩土の恐れ","迂回路":" ","備考":" ","地先名":"田辺市龍神村福井\uFF5E田辺市龍神村柳瀬"},"geometry":{"x":135.43931260697255,"y":33.890143480105195}},{"attributes":{"FID":12,"NO":"29","規制条件":"通行止め：連続雨量110mm以上、時間雨量30mm以上","路線名":"国道 ４２５号","危険内容":"落石、崩土の恐れ","迂回路":" ","備考":" ","地先名":"田辺市龍神村湯本\uFF5E和歌山県・奈良県界"},"geometry":{"x":135.56061011477334,"y":33.949969515561975}},{"attributes":{"FID":13,"NO":"30","規制条件":"通行止め：連続雨量130mm以上、時間雨量30mm以上","路線名":"国道 ４８０号","危険内容":"落石、崩土の恐れ","迂回路":" ","備考":" ","地先名":"和歌山県・大阪府界\uFF5E伊都郡かつらぎ町平"},"geometry":{"x":135.46651511641653,"y":34.347952483227928}},{"attributes":{"FID":14,"NO":"31","規制条件":"通行止め：連続雨量120mm以上、時間雨量30mm以上","路線名":"国道 ４８０号","危険内容":"落石、崩土の恐れ","迂回路":" ","備考":" ","地先名":"伊都郡高野町矢立\uFF5E伊都郡高野町高野山"},"geometry":{"x":135.53701325474702,"y":34.219438621152541}},{"attributes":{"FID":15,"NO":"32","規制条件":"通行止め：連続雨量120mm以上、時間雨量30mm以上","路線名":"国道 ４８０号","危険内容":"落石、崩土の恐れ","迂回路":" ","備考":" ","地先名":"有田郡有田川町川口\uFF5E有田郡有田川町二川"},"geometry":{"x":135.31467828231311,"y":34.048092869003625}},{"attributes":{"FID":16,"NO":"49","規制条件":" ","路線名":"主要道 樫野串本線","危険内容":"強風、高潮の恐れ","迂回路":" ","備考":"強風・越波","地先名":"東牟婁郡串本町大島\uFF5E東牟婁郡串本町出雲"},"geometry":{"x":135.79918527893432,"y":33.465419218967412}},{"attributes":{"FID":17,"NO":"50","規制条件":"通行止め：連続雨量200mm以上、時間雨量50mm以上","路線名":"主要道 潮岬周遊線","危険内容":"落石、崩土の恐れ","迂回路":" ","備考":"越波","地先名":"東牟婁郡串本町串本\uFF5E東牟婁郡串本町出雲"},"geometry":{"x":135.79299623898839,"y":33.452200553164097}},{"attributes":{"FID":18,"NO":"41","規制条件":"通行止め：連続雨量150mm以上、時間雨量40mm以上","路線名":"主要道 御坊由良線","危険内容":"落石、崩土の恐れ","迂回路":" ","備考":"越波","地先名":"日高郡由良町大引\uFF5E日高郡由良町小引"},"geometry":{"x":135.0804212541222,"y":33.969876391486999}},{"attributes":{"FID":19,"NO":"42","規制条件":"通行止め：連続雨量160mm以上、時間雨量40mm以上","路線名":"主要道 御坊美山線","危険内容":"落石、崩土の恐れ","迂回路":" ","備考":" ","地先名":"日高郡日高町川原河\uFF5E日高郡日高川町高津尾"},"geometry":{"x":135.36378621494666,"y":33.980651582258666}},{"attributes":{"FID":20,"NO":"43","規制条件":"通行止め：連続雨量160mm以上、時間雨量40mm以上","路線名":"主要道 田辺龍神線","危険内容":"落石、崩土の恐れ","迂回路":" ","備考":"区域外Ａ型１基B型1基ﾓﾆﾀｰ1人","地先名":"田辺市上秋津\uFF5E西牟婁・日高郡界"},"geometry":{"x":135.41206886320688,"y":33.770536299087453}},{"attributes":{"FID":21,"NO":"44","規制条件":" ","路線名":"主要道 白浜温泉線","危険内容":"高潮、落石、冠水の恐れ","迂回路":" ","備考":"台風時高潮の予想される場合OP+3","地先名":"西牟婁郡白浜町瀬戸\uFF5E西牟婁郡白浜町江津良"},"geometry":{"x":135.34315746609377,"y":33.689323857128393}},{"attributes":{"FID":22,"NO":"45","規制条件":"通行止め：連続雨量150mm以上、時間雨量40mm以上","路線名":"主要道 上富田すさみ線","危険内容":"落石、崩土の恐れ","迂回路":" ","備考":"区域外Ａ型１基","地先名":"西牟婁郡すさみ町防己\uFF5E西牟婁郡すさみ町江住"},"geometry":{"x":135.6203068225611,"y":33.585621733634589}},{"attributes":{"FID":23,"NO":"46","規制条件":"通行止め：連続雨量160mm以上、時間雨量40mm以上","路線名":"主要道 日置川大塔線","危険内容":"落石、崩土の恐れ","迂回路":" ","備考":"区域外Ａ型１基","地先名":"西牟婁郡白浜町田野井\uFF5E田辺市合川"},"geometry":{"x":135.49670540413496,"y":33.650811639015608}},{"attributes":{"FID":24,"NO":"47","規制条件":"通行止め：連続雨量150mm以上、時間雨量40mm以上","路線名":"主要道 すさみ古座線","危険内容":"落石、崩土の恐れ","迂回路":" ","備考":" ","地先名":"西牟婁郡すさみ町曲利\uFF5E西牟婁郡すさみ町防己"},"geometry":{"x":135.51148703675969,"y":33.560542079016443}},{"attributes":{"FID":25,"NO":"48","規制条件":"通行止め：連続雨量180mm以上、時間雨量45mm以上","路線名":"主要道 串本古座川線","危険内容":"落石、崩土の恐れ","迂回路":" ","備考":" ","地先名":"東牟婁郡古座川町下地\uFF5E東牟婁郡串本町和深"},"geometry":{"x":135.6881918480824,"y":33.558186340283108}},{"attributes":{"FID":26,"NO":"9","規制条件":"通行止め：連続雨量200mm以上、時間雨量50mm以上","路線名":"国道 ３１１号","危険内容":"落石の恐れ","迂回路":" ","備考":" ","地先名":"田辺市本宮町皆地\uFF5E田辺市本宮町本宮"},"geometry":{"x":135.73063006883001,"y":33.807159434389483}},{"attributes":{"FID":27,"NO":"10","規制条件":"通行止め：連続雨量120mm以上、時間雨量30mm以上","路線名":"国道 ３７０号","危険内容":"落石、崩土の恐れ","迂回路":" ","備考":" ","地先名":"伊都郡九度山町下古沢\uFF5E伊都郡高野町矢立"},"geometry":{"x":135.54396140686603,"y":34.256734570995647}},{"attributes":{"FID":28,"NO":"11","規制条件":"通行止め：連続雨量120mm以上","路線名":"国道 ３７０号","危険内容":"落石、崩土の恐れ","迂回路":" ","備考":" ","地先名":"海草郡紀美野町松瀬\uFF5E海草郡紀美野町毛原宮"},"geometry":{"x":135.33712269001154,"y":34.158690903930747}},{"attributes":{"FID":29,"NO":"12","規制条件":"通行止め：連続雨量120mm以上","路線名":"国道 ３７０号","危険内容":"落石、崩土の恐れ","迂回路":" ","備考":" ","地先名":"海草郡紀美野町毛原宮\uFF5E海草郡紀美野町長谷宮"},"geometry":{"x":135.46302157926038,"y":34.162833311649081}},{"attributes":{"FID":30,"NO":"13","規制条件":"通行止め：連続雨量120mm以上、時間雨量30mm以上","路線名":"国道 ３７０号","危険内容":"落石、崩土の恐れ","迂回路":" ","備考":" ","地先名":"海草郡伊都郡界\uFF5E伊都郡高野町矢立"},"geometry":{"x":135.49132826286757,"y":34.188491065151041}},{"attributes":{"FID":31,"NO":"14","規制条件":"通行止め：連続雨量120mm以上、時間雨量30mm以上","路線名":"国道 ３７１号","危険内容":"落石、崩土の恐れ","迂回路":" ","備考":" ","地先名":"橋本市向副\uFF5E伊都郡高野町高野山"},"geometry":{"x":135.61359347991694,"y":34.31234989482769}},{"attributes":{"FID":32,"NO":"15","規制条件":"通行止め：連続雨量120mm以上、時間雨量30mm以上","路線名":"国道 ３７１号","危険内容":"落石、崩土の恐れ","迂回路":" ","備考":" ","地先名":"伊都郡高野町高野山\uFF5E伊都郡かつらぎ町大字花園中南"},"geometry":{"x":135.5883690093207,"y":34.2126305697182}},{"attributes":{"FID":33,"NO":"16","規制条件":"通行止め：連続雨量120mm以上、時間雨量30mm以上","路線名":"国道 ３７１号","危険内容":"落石、崩土の恐れ","迂回路":"（県）高野天川線 野迫川村林道","備考":"高野龍神スカイライン","地先名":"伊都郡高野町高野山\uFF5E伊都郡かつらぎ町大字花園箕峠"},"geometry":{"x":135.60506744170641,"y":34.21605056811218}},{"attributes":{"FID":34,"NO":"17","規制条件":"通行止め：連続雨量120mm以上、時間雨量30mm以上","路線名":"国道 ３７１号","危険内容":"落石、崩土の恐れ","迂回路":" ","備考":"高野龍神スカイライン","地先名":"伊都郡かつらぎ町大字花園箕峠\uFF5E田辺市龍神村大熊"},"geometry":{"x":135.54676748912141,"y":34.066146126132054}},{"attributes":{"FID":35,"NO":"18","規制条件":"通行止め：連続雨量200mm以上、時間雨量50mm以上","路線名":"国道 ３７１号","危険内容":"落石、崩土の恐れ","迂回路":" ","備考":" ","地先名":"田辺市中辺路町小松原\uFF5E田辺市中辺路町高原"},"geometry":{"x":135.54780385280739,"y":33.86986822543544}},{"attributes":{"FID":36,"NO":"19","規制条件":"通行止め：連続雨量160mm以上、時間雨量40mm以上","路線名":"国道 ３７１号","危険内容":"落石、崩土の恐れ","迂回路":" ","備考":" ","地先名":"田辺市平瀬\uFF5E田辺市合川"},"geometry":{"x":135.58852363906817,"y":33.768350546076121}},{"attributes":{"FID":37,"NO":"20","規制条件":"通行止め：連続雨量180mm以上、時間雨量45mm以上","路線名":"国道 ３７１号","危険内容":"落石、崩土の恐れ","迂回路":"（町）下露三河平井線","備考":" ","地先名":"東牟婁郡古座川町平井\uFF5E東牟婁郡古座川町湯の花"},"geometry":{"x":135.673859487919,"y":33.669093608362779}},{"attributes":{"FID":38,"NO":"21","規制条件":"通行止め：連続雨量180mm以上、時間雨量45mm以上","路線名":"国道 ３７１号","危険内容":"落石、崩土の恐れ","迂回路":" ","備考":" ","地先名":"東牟婁郡古座川町三尾川\uFF5E東牟婁郡古座川町一雨"},"geometry":{"x":135.6888317928493,"y":33.558186354798941}},{"attributes":{"FID":39,"NO":"22","規制条件":"通行止め：連続雨量200mm以上、時間雨量45mm以上","路線名":"国道 ３７１号","危険内容":"落石、崩土の恐れ","迂回路":" ","備考":" ","地先名":"東牟婁郡古座川町一雨\uFF5E東牟婁郡串本町高富"},"geometry":{"x":135.74115806713147,"y":33.533820265124504}},{"attributes":{"FID":40,"NO":"23","規制条件":"通行止め：連続雨量80mm以上","路線名":"国道 ４２４号","危険内容":"落石、崩土の恐れ","迂回路":" ","備考":" ","地先名":"海南市ひや水\uFF5E海南市上谷"},"geometry":{"x":135.27156914125132,"y":34.136431924440657}},{"attributes":{"FID":41,"NO":"24","規制条件":"通行止め：連続雨量120mm以上、時間雨量30mm以上","路線名":"国道 ４２４号","危険内容":"落石、崩土の恐れ","迂回路":" ","備考":" ","地先名":"海南市有田郡界\uFF5E有田郡有田川町有原"},"geometry":{"x":135.28748813477975,"y":34.124803598826325}},{"attributes":{"FID":42,"NO":"33","規制条件":"通行止め：連続雨量120mm以上、時間雨量30mm以上","路線名":"国道 ４８０号","危険内容":"落石、崩土の恐れ","迂回路":" ","備考":" ","地先名":"有田郡有田川町二川\uFF5E有田郡有田川町清水"},"geometry":{"x":135.35748373295036,"y":34.073091023999375}},{"attributes":{"FID":43,"NO":"34","規制条件":"通行止め：連続雨量120mm以上、時間雨量30mm以上","路線名":"国道 ４８０号","危険内容":"落石、崩土の恐れ","迂回路":" ","備考":" ","地先名":"有田郡有田川町清水\uFF5E有田郡伊都郡界"},"geometry":{"x":135.43244684024,"y":34.084171483025507}},{"attributes":{"FID":44,"NO":"35","規制条件":"通行止め：連続雨量120mm以上、時間雨量30mm以上","路線名":"国道 ４８０号","危険内容":"落石、崩土の恐れ","迂回路":" ","備考":" ","地先名":"有田郡伊都郡界\uFF5E伊都郡かつらぎ町大字花園中南"},"geometry":{"x":135.51587804096141,"y":34.130698145574748}},{"attributes":{"FID":45,"NO":"36","規制条件":"通行止め：連続雨量120mm以上、時間雨量30mm以上","路線名":"主要道 かつらぎ桃山線","危険内容":"落石、崩土の恐れ","迂回路":" ","備考":" ","地先名":"紀の川市下鞆渕\uFF5E紀の川市桃山町神田"},"geometry":{"x":135.4290229285333,"y":34.211537037056516}},{"attributes":{"FID":46,"NO":"37","規制条件":"通行止め：連続雨量120mm以上","路線名":"主要道 高野口野上線","危険内容":"落石、崩土の恐れ","迂回路":" ","備考":" ","地先名":"海草郡紀美野町松瀬\uFF5E海草郡那賀郡界"},"geometry":{"x":135.3371426846407,"y":34.158800891971254}},{"attributes":{"FID":47,"NO":"38","規制条件":"通行止め：連続雨量120mm以上","路線名":"主要道 海南金屋線","危険内容":"落石、崩土の恐れ","迂回路":" ","備考":" ","地先名":"海南市別所\uFF5E海南市海草郡界"},"geometry":{"x":135.24960095206623,"y":34.13966106067619}},{"attributes":{"FID":48,"NO":"39","規制条件":"通行止め：連続雨量120mm以上","路線名":"主要道 美里龍神線","危険内容":"落石、地滑りの恐れ","迂回路":" ","備考":" ","地先名":"海草郡紀美野町樋下\uFF5E海草郡紀美野町上ヶ井"},"geometry":{"x":135.35834116385627,"y":34.148862496899596}},{"attributes":{"FID":49,"NO":"40","規制条件":"通行止め：連続雨量180mm以上、時間雨量30mm以上","路線名":"主要道 有田湯浅線","危険内容":"落石、崩土の恐れ","迂回路":" ","備考":" ","地先名":"有田市高田\uFF5E有田郡湯浅町田"},"geometry":{"x":135.13741323699293,"y":34.06349711608221}},{"attributes":{"FID":50,"NO":"51","規制条件":"通行止め：連続雨量150mm以上、時間雨量40mm以上","路線名":"主要道 那智勝浦古座川線","危険内容":"落石、崩土の恐れ","迂回路":" ","備考":" ","地先名":"東牟婁郡古座川町小森川\uFF5E東牟婁郡古座川町直見"},"geometry":{"x":135.80181921719151,"y":33.645129204584279}},{"attributes":{"FID":51,"NO":"52","規制条件":"通行止め：連続雨量160mm以上、時間雨量50mm以上","路線名":"主要道 那智勝浦古座川線","危険内容":"落石の恐れ","迂回路":" ","備考":" ","地先名":"東牟婁郡那智勝浦町南平野\uFF5E古座川町那智勝浦町界"},"geometry":{"x":135.88403199283215,"y":33.649180629804768}},{"attributes":{"FID":52,"NO":"53","規制条件":"通行止め：連続雨量180mm以上、時間雨量50mm以上","路線名":"主要道 那智勝浦熊野川線","危険内容":"落石の恐れ","迂回路":" ","備考":" ","地先名":"新宮市熊野川町小口\uFF5E新宮市熊野川町滝本"},"geometry":{"x":135.8386723702032,"y":33.75713751214068}},{"attributes":{"FID":53,"NO":"54","規制条件":"通行止め：連続雨量180mm以上、時間雨量50mm以上","路線名":"主要道 那智勝浦本宮線","危険内容":"落石、冠水の恐れ","迂回路":" ","備考":" ","地先名":"東牟婁郡那智勝浦町南大居\uFF5E東牟婁郡那智勝浦町口色川"},"geometry":{"x":135.88926339177462,"y":33.592537079389807}},{"attributes":{"FID":54,"NO":"55","規制条件":"通行止め：連続雨量250mm以上、時間雨量50mm以上","路線名":"主要道 那智山勝浦線","危険内容":"落石の恐れ","迂回路":" ","備考":" ","地先名":"東牟婁郡那智勝浦町那智山\uFF5E東牟婁郡那智勝浦町市野々"},"geometry":{"x":135.89161062040381,"y":33.671148347040713}},{"attributes":{"FID":55,"NO":"56","規制条件":"通行止め：連続雨量120mm以上、時間雨量30mm以上","路線名":"主要道 高野天川線","危険内容":"落石、崩土の恐れ","迂回路":" ","備考":" ","地先名":"伊都郡高野町高野山\uFF5E和歌山・奈良県界"},"geometry":{"x":135.61234672004832,"y":34.21869043787634}},{"attributes":{"FID":56,"NO":"73","規制条件":"通行止め：連続雨量160mm以上、時間雨量50mm以上","路線名":"県道 南平野下里停車場線","危険内容":"落石の恐れ","迂回路":" ","備考":" ","地先名":"東牟婁郡那智勝浦町南平野\uFF5E東牟婁郡那智勝浦町井鹿"},"geometry":{"x":135.88414199969489,"y":33.648680688212224}},{"attributes":{"FID":57,"NO":"74","規制条件":"通行止め：連続雨量180mm以上、時間雨量50mm以上","路線名":"県道 南平野下里停車場線","危険内容":"落石、冠水の恐れ","迂回路":" ","備考":" ","地先名":"東牟婁郡那智勝浦町南大居\uFF5E東牟婁郡那智勝浦町市屋"},"geometry":{"x":135.89375276450457,"y":33.599906358737528}},{"attributes":{"FID":58,"NO":"75","規制条件":"通行止め：連続雨量160mm以上、時間雨量50mm以上","路線名":"県道 静川請川線","危険内容":"落石、冠水の恐れ","迂回路":" ","備考":" ","地先名":"田辺市本宮町平\uFF5E田辺市本宮町耳打"},"geometry":{"x":135.74361958556102,"y":33.787631920473785}},{"attributes":{"FID":59,"NO":"76","規制条件":"通行止め：連続雨量200mm以上、時間雨量50mm以上","路線名":"県道 日置川すさみ線","危険内容":"落石、冠水の恐れ","迂回路":" ","備考":" ","地先名":"西牟婁郡白浜町塩野\uFF5E西牟婁郡白浜町伊古木"},"geometry":{"x":135.45115196584939,"y":33.569539711861758}},{"attributes":{"FID":60,"NO":"114","規制条件":"通行止め：連続雨量250mm以上","路線名":"国道 ２６号","危険内容":"大雨の恐れ","迂回路":" ","備考":" ","地先名":"大阪府泉南郡岬町孝子\uFF5E和歌山県貴志中"},"geometry":{"x":135.14813507448153,"y":34.28378246402044}},{"attributes":{"FID":61,"NO":"123","規制条件":"通行止め：連続雨量250mm以上","路線名":"国道 ４２号","危険内容":"大雨の恐れ","迂回路":" ","備考":" ","地先名":"東牟婁郡串本町田原\uFF5E東牟婁郡串本町津荷"},"geometry":{"x":135.87072695004335,"y":33.532293383622864}},{"attributes":{"FID":62,"NO":"124","規制条件":"通行止め：連続雨量250mm以上","路線名":"国道 ４２号","危険内容":"大雨の恐れ","迂回路":" ","備考":" ","地先名":"東牟婁郡串本町有田\uFF5E東牟婁郡串本町田並"},"geometry":{"x":135.73650001150568,"y":33.486105487860947}},{"attributes":{"FID":63,"NO":"125","規制条件":"通行止め：連続雨量250mm以上","路線名":"国道 ４２号","危険内容":"大雨の恐れ","迂回路":" ","備考":" ","地先名":"東牟婁郡すさみ町見老津\uFF5E同町周参見"},"geometry":{"x":135.49520896876629,"y":33.544233536431996}},{"attributes":{"FID":64,"NO":"13","規制条件":"通行止め：連続雨量120mm以上、時間雨量30mm以上","路線名":"国道 ３７０号","危険内容":"落石、崩土の恐れ","迂回路":" ","備考":" ","地先名":"海草郡伊都郡界\uFF5E伊都郡高野町矢立"},"geometry":{"x":135.53004388680813,"y":34.218688545742118}},{"attributes":{"FID":65,"NO":"14","規制条件":"通行止め：連続雨量120mm以上、時間雨量30mm以上","路線名":"国道 ３７１号","危険内容":"落石、崩土の恐れ","迂回路":" ","備考":" ","地先名":"橋本市向副\uFF5E伊都郡高野町高野山"},"geometry":{"x":135.61337658570972,"y":34.220030310440173}},{"attributes":{"FID":66,"NO":"15","規制条件":"通行止め：連続雨量120mm以上、時間雨量30mm以上","路線名":"国道 ３７１号","危険内容":"落石、崩土の恐れ","迂回路":" ","備考":" ","地先名":"伊都郡高野町高野山\uFF5E伊都郡かつらぎ町大字花園中南"},"geometry":{"x":135.57046313220795,"y":34.135498855664828}},{"attributes":{"FID":67,"NO":"16","規制条件":"通行止め：連続雨量120mm以上、時間雨量30mm以上","路線名":"国道 ３７１号","危険内容":"落石、崩土の恐れ","迂回路":"（県）高野天川線 野迫川村林道","備考":"高野龍神スカイライン","地先名":"伊都郡高野町高野山\uFF5E伊都郡かつらぎ町大字花園箕峠"},"geometry":{"x":135.56029486725538,"y":34.109841513832237}},{"attributes":{"FID":68,"NO":"57","規制条件":"通行止め：連続雨量120mm以上、時間雨量30mm以上","路線名":"主要道 泉佐野打田線","危険内容":"落石、崩土の恐れ","迂回路":"泉佐野岩出線","備考":" ","地先名":"紀の川市神通\uFF5E紀の川市重行"},"geometry":{"x":135.37319384373077,"y":34.330642298736983}},{"attributes":{"FID":69,"NO":"58","規制条件":"通行止め：連続雨量150mm以上","路線名":"主要道 泉佐野岩出線","危険内容":"落石、崩土の恐れ","迂回路":" ","備考":" ","地先名":"和歌山県・大阪府界\uFF5E岩出市根来"},"geometry":{"x":135.30731013740265,"y":34.314502616435313}},{"attributes":{"FID":70,"NO":"59","規制条件":"通行止め：連続雨量150mm以上","路線名":"主要道 和歌山貝塚線","危険内容":"落石、崩土の恐れ","迂回路":" ","備考":" ","地先名":"和歌山市滝畑"},"geometry":{"x":135.26934378124221,"y":34.30470285776606}},{"attributes":{"FID":71,"NO":"60","規制条件":"通行止め：連続雨量150mm以上","路線名":"主要道 岬加太港線","危険内容":"落石、崩土の恐れ","迂回路":"粉川加太線 （国）２６号","備考":" ","地先名":"和歌山県・大阪府界\uFF5E和歌山市深山"},"geometry":{"x":135.09327896371008,"y":34.311468083568279}},{"attributes":{"FID":72,"NO":"61","規制条件":"通行止め：連続雨量120mm以上、時間雨量30mm以上","路線名":"県道 垣内貴志川線","危険内容":"落石、崩土の恐れ","迂回路":" ","備考":" ","地先名":"紀の川市桃山町中畑\uFF5E紀の川市貴志川町井ノ口"},"geometry":{"x":135.42163431781984,"y":34.1890494066012}},{"attributes":{"FID":73,"NO":"62","規制条件":"通行止め：連続雨量120mm以上","路線名":"県道 秋月海南線","危険内容":"落石、崩土の恐れ","迂回路":" ","備考":" ","地先名":"海南市且来\uFF5E海南市神田"},"geometry":{"x":135.23235154384045,"y":34.167467528697848}},{"attributes":{"FID":74,"NO":"63","規制条件":"通行止め：連続雨量150mm以上","路線名":"県道 興加茂郷停車場線","危険内容":"落石、崩土の恐れ","迂回路":" ","備考":" ","地先名":"海南市下津町加茂郷\uFF5E海南市下津町曾根田"},"geometry":{"x":135.16682856974836,"y":34.1277205312565}},{"attributes":{"FID":75,"NO":"64","規制条件":"通行止め：連続雨量120mm以上","路線名":"県道 大崎加茂郷停車場線","危険内容":"地滑りの恐れ","迂回路":" ","備考":" ","地先名":"海南市下津町大崎"},"geometry":{"x":135.13283133405821,"y":34.133989053496663}},{"attributes":{"FID":76,"NO":"65","規制条件":"通行止め：連続雨量120mm以上","路線名":"県道 野上清水線","危険内容":"落石、崩土の恐れ","迂回路":" ","備考":" ","地先名":"海草郡・有田郡界\uFF5E海草郡紀美野町宮ノ前"},"geometry":{"x":135.3464884296188,"y":34.116199353184534}},{"attributes":{"FID":77,"NO":"66","規制条件":"通行止め：連続雨量150mm以上、時間雨量40mm以上","路線名":"県道 日の岬公園線","危険内容":"落石、崩土の恐れ","迂回路":" ","備考":"越波","地先名":"日高郡美浜町三尾\uFF5E日高郡美浜町日ノ岬"},"geometry":{"x":135.06042587643557,"y":33.880825977014801}},{"attributes":{"FID":78,"NO":"67","規制条件":"通行止め：連続雨量160mm以上、時間雨量40mm以上","路線名":"県道 近露平瀬線","危険内容":"落石、崩土の恐れ","迂回路":" ","備考":" ","地先名":"田辺市中辺路町近露\uFF5E田辺市平瀬"},"geometry":{"x":135.60416079685481,"y":33.813925789390908}},{"attributes":{"FID":79,"NO":"68","規制条件":"通行止め：連続雨量160mm以上、時間雨量40mm以上","路線名":"県道 平瀬上三栖線","危険内容":"地滑り、落石の恐れ","迂回路":" ","備考":" ","地先名":"田辺市中辺路町西谷"},"geometry":{"x":135.47281343229679,"y":33.775537113044635}},{"attributes":{"FID":80,"NO":"69","規制条件":"通行止め：連続雨量160mm以上、時間雨量40mm以上","路線名":"県道 下川上牟婁線","危険内容":"落石、崩土の恐れ","迂回路":" ","備考":" ","地先名":"田辺市鮎川\uFF5E田辺市上野"},"geometry":{"x":135.57722560444975,"y":33.738043687609206}},{"attributes":{"FID":81,"NO":"70","規制条件":"通行止め：連続雨量160mm以上、時間雨量40mm以上","路線名":"県道 下川上牟婁線","危険内容":"落石、崩土の恐れ","迂回路":" ","備考":" ","地先名":"西牟婁郡上富田町市ノ瀬"},"geometry":{"x":135.46976568596631,"y":33.714213923458125}},{"attributes":{"FID":82,"NO":"71","規制条件":"通行止め：連続雨量180mm以上、時間雨量45mm以上","路線名":"県道 古座川熊野川線","危険内容":"落石、崩土の恐れ","迂回路":"（国）３７１号 （町）下露三河平井線","備考":" ","地先名":"東牟婁郡古座川町松根\uFF5E東牟婁郡古座川町佐田"},"geometry":{"x":135.71483591731766,"y":33.670004438848167}},{"attributes":{"FID":83,"NO":"72","規制条件":"通行止め：連続雨量180mm以上、時間雨量50mm以上","路線名":"県道 高田相賀線","危険内容":"落石、冠水の恐れ","迂回路":" ","備考":" ","地先名":"新宮市相賀\uFF5E新宮市俵石"},"geometry":{"x":135.93780424108922,"y":33.744091246621764}},{"attributes":{"FID":84,"NO":"126","規制条件":"通行止め：連続雨量250mm以上","路線名":"国道 ４２号","危険内容":"大雨の恐れ","迂回路":" ","備考":" ","地先名":"西東牟婁郡白浜町志原\uFF5E西牟婁郡白浜町富田字高瀬"},"geometry":{"x":135.40280398869581,"y":33.636771092901064}},{"attributes":{"FID":85,"NO":"127","規制条件":"通行止め：連続雨量250mm以上","路線名":"国道 ４２号","危険内容":"大雨の恐れ","迂回路":" ","備考":" ","地先名":"日高郡みなべ町山内\uFF5E日高郡みなべ町東岩代"},"geometry":{"x":135.28477950574427,"y":33.783152008602201}},{"attributes":{"FID":86,"NO":"128","規制条件":"通行止め：連続雨量250mm以上","路線名":"国道 ４２号","危険内容":"大雨の恐れ","迂回路":" ","備考":" ","地先名":"日高郡日高町池田\uFF5E由良町里"},"geometry":{"x":135.12342777322141,"y":33.961548298464024}},{"attributes":{"FID":87,"NO":"129","規制条件":"通行止め：連続雨量250mm以上","路線名":"国道 ４２号","危険内容":"大雨の恐れ","迂回路":" ","備考":" ","地先名":"日高郡由良町畑\uFF5E有田郡広川町河瀬"},"geometry":{"x":135.19009063428183,"y":34.002365201512532}},{"attributes":{"FID":88,"NO":"1","規制条件":"通行止め：連続雨量200mm以上、時間雨量50mm以上","路線名":"国道 １６８号","危険内容":"落石、冠水の恐れ","迂回路":" ","備考":" ","地先名":"新宮市南磐盾\uFF5E新宮市熊野川町・田辺市境界"},"geometry":{"x":135.80942239352152,"y":33.833318305650529}},{"attributes":{"FID":89,"NO":"2","規制条件":"通行止め：連続雨量180mm以上、時間雨量50mm以上","路線名":"国道 １６８号","危険内容":"落石、冠水の恐れ","迂回路":" ","備考":" ","地先名":"新宮市熊野川町・田辺市境界\uFF5E田辺市本宮町土河屋（県境）"},"geometry":{"x":135.76020486782303,"y":33.887481101512918}},{"attributes":{"FID":90,"NO":"3","規制条件":"通行止め：連続雨量180mm以上、時間雨量50mm以上","路線名":"国道 １６９号","危険内容":"落石、冠水の恐れ","迂回路":" ","備考":" ","地先名":"新宮市熊野川町宮井\uFF5E新宮市熊野川町九重（県境）"},"geometry":{"x":135.8571069403427,"y":33.873624880941769}},{"attributes":{"FID":91,"NO":"4","規制条件":"通行止め：連続雨量180mm以上、時間雨量50mm以上","路線名":"国道 １６９号","危険内容":"落石、冠水の恐れ","迂回路":" ","備考":" ","地先名":"新宮市熊野川町玉置口(県境）\uFF5E新宮市熊野川町田戸（県境）"},"geometry":{"x":135.88113349034469,"y":33.915090782539245}},{"attributes":{"FID":92,"NO":"5","規制条件":"通行止め：連続雨量180mm以上、時間雨量50mm以上","路線名":"国道 １６９号","危険内容":"落石、冠水の恐れ","迂回路":" ","備考":" ","地先名":"東牟婁郡北山村下尾井\uFF5E東牟婁郡北山村小松"},"geometry":{"x":135.91741016485943,"y":33.920760982461076}},{"attributes":{"FID":93,"NO":"6","規制条件":"通行止め：連続雨量200mm以上、時間雨量50mm以上","路線名":"国道 ３１１号","危険内容":"落石、崩土の恐れ","迂回路":" ","備考":"区域外に情報板A型2基B型1基","地先名":"田辺市鮎川\uFF5E田辺市中辺路町栗栖川"},"geometry":{"x":135.51638914103421,"y":33.791316330609021}},{"attributes":{"FID":94,"NO":"7","規制条件":"通行止め：連続雨量200mm以上、時間雨量50mm以上","路線名":"国道 ３１１号","危険内容":"落石、崩土の恐れ","迂回路":" ","備考":" ","地先名":"田辺市中辺路町栗栖川\uFF5E田辺市中辺路町・本宮町境界"},"geometry":{"x":135.67187466265523,"y":33.822156410105833}},{"attributes":{"FID":95,"NO":"8","規制条件":"通行止め：連続雨量160mm以上、時間雨量50mm以上","路線名":"国道 ３１１号","危険内容":"落石の恐れ","迂回路":" ","備考":" ","地先名":"田辺市中辺路町・本宮町境界\uFF5E田辺市本宮町皆地"},"geometry":{"x":135.72990012936219,"y":33.807239408734411}},{"attributes":{"FID":96,"NO":"9","規制条件":"通行止め：連続雨量200mm以上、時間雨量50mm以上","路線名":"国道 ３１１号","危険内容":"落石の恐れ","迂回路":" ","備考":" ","地先名":"田辺市本宮町皆地\uFF5E田辺市本宮町本宮"},"geometry":{"x":135.77638549109474,"y":33.82601836692892}},{"attributes":{"FID":97,"NO":"10","規制条件":"通行止め：連続雨量120mm以上、時間雨量30mm以上","路線名":"国道 ３７０号","危険内容":"落石、崩土の恐れ","迂回路":" ","備考":" ","地先名":"伊都郡九度山町下古沢\uFF5E伊都郡高野町矢立"},"geometry":{"x":135.53701325474702,"y":34.219438621152541}},{"attributes":{"FID":98,"NO":"11","規制条件":"通行止め：連続雨量120mm以上","路線名":"国道 ３７０号","危険内容":"落石、崩土の恐れ","迂回路":" ","備考":" ","地先名":"海草郡紀美野町松瀬\uFF5E海草郡紀美野町毛原宮"},"geometry":{"x":135.46377148744577,"y":34.163633238569233}},{"attributes":{"FID":99,"NO":"12","規制条件":"通行止め：連続雨量120mm以上","路線名":"国道 ３７０号","危険内容":"落石、崩土の恐れ","迂回路":" ","備考":" ","地先名":"海草郡紀美野町毛原宮\uFF5E海草郡紀美野町長谷宮"},"geometry":{"x":135.48265922771202,"y":34.182171579541695}},{"attributes":{"FID":100,"NO":"17","規制条件":"通行止め：連続雨量120mm以上、時間雨量30mm以上","路線名":"国道 ３７１号","危険内容":"落石、崩土の恐れ","迂回路":" ","備考":"高野龍神スカイライン","地先名":"伊都郡かつらぎ町大字花園箕峠\uFF5E田辺市龍神村大熊"},"geometry":{"x":135.56243850950705,"y":33.993934612616876}},{"attributes":{"FID":101,"NO":"18","規制条件":"通行止め：連続雨量200mm以上、時間雨量50mm以上","路線名":"国道 ３７１号","危険内容":"落石、崩土の恐れ","迂回路":" ","備考":" ","地先名":"田辺市中辺路町小松原\uFF5E田辺市中辺路町高原"},"geometry":{"x":135.52519806437161,"y":33.800925452210606}},{"attributes":{"FID":102,"NO":"19","規制条件":"通行止め：連続雨量160mm以上、時間雨量40mm以上","路線名":"国道 ３７１号","危険内容":"落石、崩土の恐れ","迂回路":" ","備考":" ","地先名":"田辺市平瀬\uFF5E田辺市合川"},"geometry":{"x":135.56830796031983,"y":33.689298948356765}},{"attributes":{"FID":103,"NO":"20","規制条件":"通行止め：連続雨量180mm以上、時間雨量45mm以上","路線名":"国道 ３７１号","危険内容":"落石、崩土の恐れ","迂回路":"（町）下露三河平井線","備考":" ","地先名":"東牟婁郡古座川町平井\uFF5E東牟婁郡古座川町湯の花"},"geometry":{"x":135.68527063035862,"y":33.603561200607857}},{"attributes":{"FID":104,"NO":"37","規制条件":"通行止め：連続雨量120mm以上","路線名":"主要道 高野口野上線","危険内容":"落石、崩土の恐れ","迂回路":" ","備考":" ","地先名":"海草郡紀美野町松瀬\uFF5E海草郡那賀郡界"},"geometry":{"x":135.41461504824318,"y":34.18546965016013}},{"attributes":{"FID":105,"NO":"38","規制条件":"通行止め：連続雨量120mm以上","路線名":"主要道 海南金屋線","危険内容":"落石、崩土の恐れ","迂回路":" ","備考":" ","地先名":"海南市別所\uFF5E海南市海草郡界"},"geometry":{"x":135.24224216684976,"y":34.122222862148689}},{"attributes":{"FID":106,"NO":"39","規制条件":"通行止め：連続雨量120mm以上","路線名":"主要道 美里龍神線","危険内容":"落石、地滑りの恐れ","迂回路":" ","備考":" ","地先名":"海草郡紀美野町樋下\uFF5E海草郡紀美野町上ヶ井"},"geometry":{"x":135.37428070665447,"y":34.120586050582993}},{"attributes":{"FID":107,"NO":"40","規制条件":"通行止め：連続雨量180mm以上、時間雨量30mm以上","路線名":"主要道 有田湯浅線","危険内容":"落石、崩土の恐れ","迂回路":" ","備考":" ","地先名":"有田市高田\uFF5E有田郡湯浅町田"},"geometry":{"x":135.15680195252733,"y":34.050998964476399}},{"attributes":{"FID":108,"NO":"41","規制条件":"通行止め：連続雨量150mm以上、時間雨量40mm以上","路線名":"主要道 御坊由良線","危険内容":"落石、崩土の恐れ","迂回路":" ","備考":"越波","地先名":"日高郡由良町大引\uFF5E日高郡由良町小引"},"geometry":{"x":135.08865020491342,"y":33.980095424466484}},{"attributes":{"FID":109,"NO":"42","規制条件":"通行止め：連続雨量160mm以上、時間雨量40mm以上","路線名":"主要道 御坊美山線","危険内容":"落石、崩土の恐れ","迂回路":" ","備考":" ","地先名":"日高郡日高町川原河\uFF5E日高郡日高川町高津尾"},"geometry":{"x":135.29182310379915,"y":33.961492107927349}},{"attributes":{"FID":110,"NO":"43","規制条件":"通行止め：連続雨量160mm以上、時間雨量40mm以上","路線名":"主要道 田辺龍神線","危険内容":"落石、崩土の恐れ","迂回路":" ","備考":"区域外Ａ型１基B型1基ﾓﾆﾀｰ1人","地先名":"田辺市上秋津\uFF5E西牟婁・日高郡界"},"geometry":{"x":135.44357383291134,"y":33.841199077230648}},{"attributes":{"FID":111,"NO":"44","規制条件":" ","路線名":"主要道 白浜温泉線","危険内容":"高潮、落石、冠水の恐れ","迂回路":" ","備考":"台風時高潮の予想される場合OP+3","地先名":"西牟婁郡白浜町瀬戸\uFF5E西牟婁郡白浜町江津良"},"geometry":{"x":135.35232655094615,"y":33.693043646398024}},{"attributes":{"FID":112,"NO":"61","規制条件":"通行止め：連続雨量120mm以上、時間雨量30mm以上","路線名":"県道 垣内貴志川線","危険内容":"落石、崩土の恐れ","迂回路":" ","備考":" ","地先名":"紀の川市桃山町中畑\uFF5E紀の川市貴志川町井ノ口"},"geometry":{"x":135.32353263365911,"y":34.196326344712944}},{"attributes":{"FID":113,"NO":"62","規制条件":"通行止め：連続雨量120mm以上","路線名":"県道 秋月海南線","危険内容":"落石、崩土の恐れ","迂回路":" ","備考":" ","地先名":"海南市且来\uFF5E海南市神田"},"geometry":{"x":135.23071172647309,"y":34.16626762697021}},{"attributes":{"FID":114,"NO":"63","規制条件":"通行止め：連続雨量150mm以上","路線名":"県道 興加茂郷停車場線","危険内容":"落石、崩土の恐れ","迂回路":" ","備考":" ","地先名":"海南市下津町加茂郷\uFF5E海南市下津町曾根田"},"geometry":{"x":135.19565606441392,"y":34.127361225126258}},{"attributes":{"FID":115,"NO":"64","規制条件":"通行止め：連続雨量120mm以上","路線名":"県道 大崎加茂郷停車場線","危険内容":"地滑りの恐れ","迂回路":" ","備考":" ","地先名":"海南市下津町大崎"},"geometry":{"x":135.15304987326786,"y":34.124660564789323}},{"attributes":{"FID":116,"NO":"65","規制条件":"通行止め：連続雨量120mm以上","路線名":"県道 野上清水線","危険内容":"落石、崩土の恐れ","迂回路":" ","備考":" ","地先名":"海草郡・有田郡界\uFF5E海草郡紀美野町宮ノ前"},"geometry":{"x":135.32764434389446,"y":34.133583521675497}},{"attributes":{"FID":117,"NO":"66","規制条件":"通行止め：連続雨量150mm以上、時間雨量40mm以上","路線名":"県道 日の岬公園線","危険内容":"落石、崩土の恐れ","迂回路":" ","備考":"越波","地先名":"日高郡美浜町三尾\uFF5E日高郡美浜町日ノ岬"},"geometry":{"x":135.07890395032695,"y":33.890605290295348}},{"attributes":{"FID":118,"NO":"21","規制条件":"通行止め：連続雨量180mm以上、時間雨量45mm以上","路線名":"国道 ３７１号","危険内容":"落石、崩土の恐れ","迂回路":" ","備考":" ","地先名":"東牟婁郡古座川町三尾川\uFF5E東牟婁郡古座川町一雨"},"geometry":{"x":135.74110807047208,"y":33.533850260638495}},{"attributes":{"FID":119,"NO":"22","規制条件":"通行止め：連続雨量200mm以上、時間雨量45mm以上","路線名":"国道 ３７１号","危険内容":"落石、崩土の恐れ","迂回路":" ","備考":" ","地先名":"東牟婁郡古座川町一雨\uFF5E東牟婁郡串本町高富"},"geometry":{"x":135.76279782741827,"y":33.483556368967299}},{"attributes":{"FID":120,"NO":"23","規制条件":"通行止め：連続雨量80mm以上","路線名":"国道 ４２４号","危険内容":"落石、崩土の恐れ","迂回路":" ","備考":" ","地先名":"海南市ひや水\uFF5E海南市上谷"},"geometry":{"x":135.287348144361,"y":34.124883586616349}},{"attributes":{"FID":121,"NO":"24","規制条件":"通行止め：連続雨量120mm以上、時間雨量30mm以上","路線名":"国道 ４２４号","危険内容":"落石、崩土の恐れ","迂回路":" ","備考":" ","地先名":"海南市有田郡界\uFF5E有田郡有田川町有原"},"geometry":{"x":135.27940998942896,"y":34.08977736737166}},{"attributes":{"FID":122,"NO":"25","規制条件":"通行止め：連続雨量160mm以上、時間雨量30mm以上","路線名":"国道 ４２４号","危険内容":"落石、崩土の恐れ","迂回路":" ","備考":" ","地先名":"田辺市龍神村小家\uFF5E田辺市龍神村福井"},"geometry":{"x":135.43973255613557,"y":33.89058344018104}},{"attributes":{"FID":123,"NO":"26","規制条件":"通行止め：連続雨量160mm以上、時間雨量30mm以上","路線名":"国道 ４２４号","危険内容":"落石、崩土の恐れ","迂回路":" ","備考":" ","地先名":"田辺市龍神村福井\uFF5E日高郡みなべ町清川"},"geometry":{"x":135.39845736319944,"y":33.853086718751221}},{"attributes":{"FID":124,"NO":"27","規制条件":"通行止め：連続雨量160mm以上、時間雨量30mm以上","路線名":"国道 ４２４号","危険内容":"落石、崩土の恐れ","迂回路":" ","備考":" ","地先名":"日高郡みなべ町清川\uFF5E日高郡みなべ町西本庄"},"geometry":{"x":135.32845495225482,"y":33.806620357030475}},{"attributes":{"FID":125,"NO":"28","規制条件":"通行止め：連続雨量160mm以上、時間雨量30mm以上","路線名":"国道 ４２５号","危険内容":"落石、崩土の恐れ","迂回路":" ","備考":" ","地先名":"田辺市龍神村福井\uFF5E田辺市龍神村柳瀬"},"geometry":{"x":135.46967031360037,"y":33.879645349666674}},{"attributes":{"FID":126,"NO":"29","規制条件":"通行止め：連続雨量110mm以上、時間雨量30mm以上","路線名":"国道 ４２５号","危険内容":"落石、崩土の恐れ","迂回路":" ","備考":" ","地先名":"田辺市龍神村湯本\uFF5E和歌山県・奈良県界"},"geometry":{"x":135.63890286951676,"y":33.963659766132629}},{"attributes":{"FID":127,"NO":"30","規制条件":"通行止め：連続雨量130mm以上、時間雨量30mm以上","路線名":"国道 ４８０号","危険内容":"落石、崩土の恐れ","迂回路":" ","備考":" ","地先名":"和歌山県・大阪府界\uFF5E伊都郡かつらぎ町平"},"geometry":{"x":135.4791844478905,"y":34.334864254423891}},{"attributes":{"FID":128,"NO":"31","規制条件":"通行止め：連続雨量120mm以上、時間雨量30mm以上","路線名":"国道 ４８０号","危険内容":"落石、崩土の恐れ","迂回路":" ","備考":" ","地先名":"伊都郡高野町矢立\uFF5E伊都郡高野町高野山"},"geometry":{"x":135.58842900043291,"y":34.212740558690108}},{"attributes":{"FID":129,"NO":"32","規制条件":"通行止め：連続雨量120mm以上、時間雨量30mm以上","路線名":"国道 ４８０号","危険内容":"落石、崩土の恐れ","迂回路":" ","備考":" ","地先名":"有田郡有田川町川口\uFF5E有田郡有田川町二川"},"geometry":{"x":135.35784367432589,"y":34.073920938626188}},{"attributes":{"FID":130,"NO":"33","規制条件":"通行止め：連続雨量120mm以上、時間雨量30mm以上","路線名":"国道 ４８０号","危険内容":"落石、崩土の恐れ","迂回路":" ","備考":" ","地先名":"有田郡有田川町二川\uFF5E有田郡有田川町清水"},"geometry":{"x":135.42869721511062,"y":34.082701563160121}},{"attributes":{"FID":131,"NO":"34","規制条件":"通行止め：連続雨量120mm以上、時間雨量30mm以上","路線名":"国道 ４８０号","危険内容":"落石、崩土の恐れ","迂回路":" ","備考":" ","地先名":"有田郡有田川町清水\uFF5E有田郡伊都郡界"},"geometry":{"x":135.57060312633246,"y":34.135308880288221}},{"attributes":{"FID":132,"NO":"35","規制条件":"通行止め：連続雨量120mm以上、時間雨量30mm以上","路線名":"国道 ４８０号","危険内容":"落石、崩土の恐れ","迂回路":" ","備考":" ","地先名":"有田郡伊都郡界\uFF5E伊都郡かつらぎ町大字花園中南"},"geometry":{"x":135.5706031243422,"y":34.135368873526552}},{"attributes":{"FID":133,"NO":"36","規制条件":"通行止め：連続雨量120mm以上、時間雨量30mm以上","路線名":"主要道 かつらぎ桃山線","危険内容":"落石、崩土の恐れ","迂回路":" ","備考":" ","地先名":"紀の川市下鞆渕\uFF5E紀の川市桃山町神田"},"geometry":{"x":135.35667871247662,"y":34.227433587535977}},{"attributes":{"FID":134,"NO":"45","規制条件":"通行止め：連続雨量150mm以上、時間雨量40mm以上","路線名":"主要道 上富田すさみ線","危険内容":"落石、崩土の恐れ","迂回路":" ","備考":"区域外Ａ型１基","地先名":"西牟婁郡すさみ町防己\uFF5E西牟婁郡すさみ町江住"},"geometry":{"x":135.60270061352676,"y":33.5152692013042}},{"attributes":{"FID":135,"NO":"46","規制条件":"通行止め：連続雨量160mm以上、時間雨量40mm以上","路線名":"主要道 日置川大塔線","危険内容":"落石、崩土の恐れ","迂回路":" ","備考":"区域外Ａ型１基","地先名":"西牟婁郡白浜町田野井\uFF5E田辺市合川"},"geometry":{"x":135.44779159042037,"y":33.590257316834887}},{"attributes":{"FID":136,"NO":"47","規制条件":"通行止め：連続雨量150mm以上、時間雨量40mm以上","路線名":"主要道 すさみ古座線","危険内容":"落石、崩土の恐れ","迂回路":" ","備考":" ","地先名":"西牟婁郡すさみ町曲利\uFF5E西牟婁郡すさみ町防己"},"geometry":{"x":135.60061908694396,"y":33.568183238347352}},{"attributes":{"FID":137,"NO":"48","規制条件":"通行止め：連続雨量180mm以上、時間雨量45mm以上","路線名":"主要道 串本古座川線","危険内容":"落石、崩土の恐れ","迂回路":" ","備考":" ","地先名":"東牟婁郡古座川町下地\uFF5E東牟婁郡串本町和深"},"geometry":{"x":135.65616638741199,"y":33.503211757704648}},{"attributes":{"FID":138,"NO":"49","規制条件":" ","路線名":"主要道 樫野串本線","危険内容":"強風、高潮の恐れ","迂回路":" ","備考":"強風・越波","地先名":"東牟婁郡串本町大島\uFF5E東牟婁郡串本町出雲"},"geometry":{"x":135.78899639873373,"y":33.457919824349545}},{"attributes":{"FID":139,"NO":"50","規制条件":"通行止め：連続雨量200mm以上、時間雨量50mm以上","路線名":"主要道 潮岬周遊線","危険内容":"落石、崩土の恐れ","迂回路":" ","備考":"越波","地先名":"東牟婁郡串本町串本\uFF5E東牟婁郡串本町出雲"},"geometry":{"x":135.7891563894762,"y":33.457779843597521}},{"attributes":{"FID":140,"NO":"51","規制条件":"通行止め：連続雨量150mm以上、時間雨量40mm以上","路線名":"主要道 那智勝浦古座川線","危険内容":"落石、崩土の恐れ","迂回路":" ","備考":" ","地先名":"東牟婁郡古座川町小森川\uFF5E東牟婁郡古座川町直見"},"geometry":{"x":135.77171511890739,"y":33.543489879270247}},{"attributes":{"FID":141,"NO":"52","規制条件":"通行止め：連続雨量160mm以上、時間雨量50mm以上","路線名":"主要道 那智勝浦古座川線","危険内容":"落石の恐れ","迂回路":" ","備考":" ","地先名":"東牟婁郡那智勝浦町南平野\uFF5E古座川町那智勝浦町界"},"geometry":{"x":135.80192920900376,"y":33.645089211566628}},{"attributes":{"FID":142,"NO":"53","規制条件":"通行止め：連続雨量180mm以上、時間雨量50mm以上","路線名":"主要道 那智勝浦熊野川線","危険内容":"落石の恐れ","迂回路":" ","備考":" ","地先名":"新宮市熊野川町小口\uFF5E新宮市熊野川町滝本"},"geometry":{"x":135.82123540208428,"y":33.710592323979526}},{"attributes":{"FID":143,"NO":"54","規制条件":"通行止め：連続雨量180mm以上、時間雨量50mm以上","路線名":"主要道 那智勝浦本宮線","危険内容":"落石、冠水の恐れ","迂回路":" ","備考":" ","地先名":"東牟婁郡那智勝浦町南大居\uFF5E東牟婁郡那智勝浦町口色川"},"geometry":{"x":135.85881319863617,"y":33.678816738838165}},{"attributes":{"FID":144,"NO":"55","規制条件":"通行止め：連続雨量250mm以上、時間雨量50mm以上","路線名":"主要道 那智山勝浦線","危険内容":"落石の恐れ","迂回路":" ","備考":" ","地先名":"東牟婁郡那智勝浦町那智山\uFF5E東牟婁郡那智勝浦町市野々"},"geometry":{"x":135.91460909757788,"y":33.657090445427386}},{"attributes":{"FID":145,"NO":"56","規制条件":"通行止め：連続雨量120mm以上、時間雨量30mm以上","路線名":"主要道 高野天川線","危険内容":"落石、崩土の恐れ","迂回路":" ","備考":" ","地先名":"伊都郡高野町高野山\uFF5E和歌山・奈良県界"},"geometry":{"x":135.63806486552224,"y":34.207192326967679}},{"attributes":{"FID":146,"NO":"57","規制条件":"通行止め：連続雨量120mm以上、時間雨量30mm以上","路線名":"主要道 泉佐野打田線","危険内容":"落石、崩土の恐れ","迂回路":"泉佐野岩出線","備考":" ","地先名":"紀の川市神通\uFF5E紀の川市重行"},"geometry":{"x":135.37094547936499,"y":34.287367140790792}},{"attributes":{"FID":147,"NO":"58","規制条件":"通行止め：連続雨量150mm以上","路線名":"主要道 泉佐野岩出線","危険内容":"落石、崩土の恐れ","迂回路":" ","備考":" ","地先名":"和歌山県・大阪府界\uFF5E岩出市根来"},"geometry":{"x":135.30414110743766,"y":34.293614906645033}},{"attributes":{"FID":148,"NO":"59","規制条件":"通行止め：連続雨量150mm以上","路線名":"主要道 和歌山貝塚線","危険内容":"落石、崩土の恐れ","迂回路":" ","備考":" ","地先名":"和歌山市滝畑"},"geometry":{"x":135.27331373175426,"y":34.295723964127795}},{"attributes":{"FID":149,"NO":"60","規制条件":"通行止め：連続雨量150mm以上","路線名":"主要道 岬加太港線","危険内容":"落石、崩土の恐れ","迂回路":"粉川加太線 （国）２６号","備考":" ","地先名":"和歌山県・大阪府界\uFF5E和歌山市深山"},"geometry":{"x":135.07664099742126,"y":34.293969687436096}},{"attributes":{"FID":150,"NO":"67","規制条件":"通行止め：連続雨量160mm以上、時間雨量40mm以上","路線名":"県道 近露平瀬線","危険内容":"落石、崩土の恐れ","迂回路":" ","備考":" ","地先名":"田辺市中辺路町近露\uFF5E田辺市平瀬"},"geometry":{"x":135.58872361914132,"y":33.768430541652222}},{"attributes":{"FID":151,"NO":"68","規制条件":"通行止め：連続雨量160mm以上、時間雨量40mm以上","路線名":"県道 平瀬上三栖線","危険内容":"地滑り、落石の恐れ","迂回路":" ","備考":" ","地先名":"田辺市中辺路町西谷"},"geometry":{"x":135.47970289341723,"y":33.773737471156736}},{"attributes":{"FID":152,"NO":"69","規制条件":"通行止め：連続雨量160mm以上、時間雨量40mm以上","路線名":"県道 下川上牟婁線","危険内容":"落石、崩土の恐れ","迂回路":" ","備考":" ","地先名":"田辺市鮎川\uFF5E田辺市上野"},"geometry":{"x":135.49639297170626,"y":33.72677311785398}},{"attributes":{"FID":153,"NO":"70","規制条件":"通行止め：連続雨量160mm以上、時間雨量40mm以上","路線名":"県道 下川上牟婁線","危険内容":"落石、崩土の恐れ","迂回路":" ","備考":" ","地先名":"西牟婁郡上富田町市ノ瀬"},"geometry":{"x":135.47828486938948,"y":33.71663384486942}},{"attributes":{"FID":154,"NO":"71","規制条件":"通行止め：連続雨量180mm以上、時間雨量45mm以上","路線名":"県道 古座川熊野川線","危険内容":"落石、崩土の恐れ","迂回路":"（国）３７１号 （町）下露三河平井線","備考":" ","地先名":"東牟婁郡古座川町松根\uFF5E東牟婁郡古座川町佐田"},"geometry":{"x":135.69665983693218,"y":33.597702114548149}},{"attributes":{"FID":155,"NO":"72","規制条件":"通行止め：連続雨量180mm以上、時間雨量50mm以上","路線名":"県道 高田相賀線","危険内容":"落石、冠水の恐れ","迂回路":" ","備考":" ","地先名":"新宮市相賀\uFF5E新宮市俵石"},"geometry":{"x":135.91744715326396,"y":33.708924713997035}},{"attributes":{"FID":156,"NO":"73","規制条件":"通行止め：連続雨量160mm以上、時間雨量50mm以上","路線名":"県道 南平野下里停車場線","危険内容":"落石の恐れ","迂回路":" ","備考":" ","地先名":"東牟婁郡那智勝浦町南平野\uFF5E東牟婁郡那智勝浦町井鹿"},"geometry":{"x":135.8937027635929,"y":33.60006633972246}},{"attributes":{"FID":157,"NO":"74","規制条件":"通行止め：連続雨量180mm以上、時間雨量50mm以上","路線名":"県道 南平野下里停車場線","危険内容":"落石、冠水の恐れ","迂回路":" ","備考":" ","地先名":"東牟婁郡那智勝浦町南大居\uFF5E東牟婁郡那智勝浦町市屋"},"geometry":{"x":135.91850098759372,"y":33.589018140664095}},{"attributes":{"FID":158,"NO":"75","規制条件":"通行止め：連続雨量160mm以上、時間雨量50mm以上","路線名":"県道 静川請川線","危険内容":"落石、冠水の恐れ","迂回路":" ","備考":" ","地先名":"田辺市本宮町平\uFF5E田辺市本宮町耳打"},"geometry":{"x":135.78272526029022,"y":33.816359595037312}},{"attributes":{"FID":159,"NO":"76","規制条件":"通行止め：連続雨量200mm以上、時間雨量50mm以上","路線名":"県道 日置川すさみ線","危険内容":"落石、冠水の恐れ","迂回路":" ","備考":" ","地先名":"西牟婁郡白浜町塩野\uFF5E西牟婁郡白浜町伊古木"},"geometry":{"x":135.46382152044708,"y":33.549292263204528}},{"attributes":{"FID":160,"NO":"114","規制条件":"通行止め：連続雨量250mm以上","路線名":"国道 ２６号","危険内容":"大雨の恐れ","迂回路":" ","備考":" ","地先名":"大阪府泉南郡岬町孝子\uFF5E和歌山県貴志中"},"geometry":{"x":135.14374618561575,"y":34.261724860282769}},{"attributes":{"FID":161,"NO":"123","規制条件":"通行止め：連続雨量250mm以上","路線名":"国道 ４２号","危険内容":"大雨の恐れ","迂回路":" ","備考":" ","地先名":"東牟婁郡串本町田原\uFF5E東牟婁郡串本町津荷"},"geometry":{"x":135.84450963196116,"y":33.519244242908201}},{"attributes":{"FID":162,"NO":"124","規制条件":"通行止め：連続雨量250mm以上","路線名":"国道 ４２号","危険内容":"大雨の恐れ","迂回路":" ","備考":" ","地先名":"東牟婁郡串本町有田\uFF5E東牟婁郡串本町田並"},"geometry":{"x":135.72344105555231,"y":33.488634909389759}},{"attributes":{"FID":163,"NO":"125","規制条件":"通行止め：連続雨量250mm以上","路線名":"国道 ４２号","危険内容":"大雨の恐れ","迂回路":" ","備考":" ","地先名":"東牟婁郡すさみ町見老津\uFF5E同町周参見"},"geometry":{"x":135.573623080678,"y":33.516628392510121}},{"attributes":{"FID":164,"NO":"126","規制条件":"通行止め：連続雨量250mm以上","路線名":"国道 ４２号","危険内容":"大雨の恐れ","迂回路":" ","備考":" ","地先名":"西東牟婁郡白浜町志原\uFF5E西牟婁郡白浜町富田字高瀬"},"geometry":{"x":135.42907378542651,"y":33.57236889796814}},{"attributes":{"FID":165,"NO":"127","規制条件":"通行止め：連続雨量250mm以上","路線名":"国道 ４２号","危険内容":"大雨の恐れ","迂回路":" ","備考":" ","地先名":"日高郡みなべ町山内\uFF5E日高郡みなべ町東岩代"},"geometry":{"x":135.31096746366765,"y":33.77595340760179}},{"attributes":{"FID":166,"NO":"128","規制条件":"通行止め：連続雨量250mm以上","路線名":"国道 ４２号","危険内容":"大雨の恐れ","迂回路":" ","備考":" ","地先名":"日高郡日高町池田\uFF5E由良町里"},"geometry":{"x":135.14116717186423,"y":33.932401982283764}},{"attributes":{"FID":167,"NO":"129","規制条件":"通行止め：連続雨量250mm以上","路線名":"国道 ４２号","危険内容":"大雨の恐れ","迂回路":" ","備考":" ","地先名":"日高郡由良町畑\uFF5E有田郡広川町河瀬"},"geometry":{"x":135.15355440606228,"y":33.984346407839723}}]}